dj_datatables_view/__init__.py
dj_datatables_view/base_datatable_view.py
dj_datatables_view/mixins.py
dj_datatables_view-0.1.8.dist-info/LICENSE
dj_datatables_view-0.1.8.dist-info/WHEEL
dj_datatables_view-0.1.8.dist-info/METADATA
dj_datatables_view-0.1.8.dist-info/RECORD
