Metadata-Version: 2.1
Name: dj-datatables-view
Version: 0.1.8
Summary: Django datatables view fork from django-datatables-view
Home-page: https://gitlab.com/longbowou/django-datatables-view
License: MIT
Keywords: django,datatable,view
Author: Longbowou
Author-email: blandedaniel@gmail.com
Maintainer: Longbowou
Maintainer-email: blandedaniel@gmail.com
Requires-Python: >=3.5,<4.0
Classifier: License :: OSI Approved :: MIT License
Classifier: Programming Language :: Python :: 3
Classifier: Programming Language :: Python :: 3.10
Classifier: Programming Language :: Python :: 3.5
Classifier: Programming Language :: Python :: 3.6
Classifier: Programming Language :: Python :: 3.7
Classifier: Programming Language :: Python :: 3.8
Classifier: Programming Language :: Python :: 3.9
Project-URL: Bug Tracker, https://gitlab.com/longbowou/django-datatables-view/issues
Project-URL: Repository, https://gitlab.com/longbowou/django-datatables-view
